seconds/__init__.py
seconds/seconds.py
seconds/version.py
seconds-0.1.0.dist-info/LICENSE
seconds-0.1.0.dist-info/METADATA
seconds-0.1.0.dist-info/WHEEL
seconds-0.1.0.dist-info/top_level.txt
seconds-0.1.0.dist-info/RECORD
