Metadata-Version: 2.1
Name: seconds
Version: 0.1.0
Summary: Seconds is a utility package to transform seconds to minutes, hours, etc. and vice versa quickly, easily, understandable by humans and without external dependencies!
Home-page: https://github.com/NTBBloodbath/Seconds
Author: NTBBloodbath
Author-email: bloodbathalchemist@protonmail.com
License: MIT
Platform: UNKNOWN
Classifier: Programming Language :: Python :: 3
Classifier: Programming Language :: Python :: 3.6
Classifier: Programming Language :: Python :: 3.7
Classifier: Programming Language :: Python :: 3.8
Classifier: Programming Language :: Python :: 3.9
Classifier: Development Status :: 5 - Production/Stable
Classifier: Environment :: Console
Classifier: Intended Audience :: Developers
Classifier: License :: OSI Approved :: MIT License
Classifier: Operating System :: OS Independent
Classifier: Topic :: Utilities
